focuspro_data533-0.0.1.dist-info/licenses/LICENSE
project/__init__.py
project/discover.py
project/run_demo.py
project/analytics/__init__.py
project/analytics/distraction.py
project/analytics/exceptions.py
project/analytics/focuscore.py
project/analytics/weekly_report.py
project/core/__init__.py
project/core/exceptions.py
project/core/focus_session.py
project/core/habit.py
project/core/task.py
project/core/tasks.py
project/planner/__init__.py
project/planner/base_planner.py
project/planner/daily_plan.py
project/planner/exceptions.py
project/planner/priority_strategy.py
project/planner/schedulers.py
focuspro_data533-0.0.1.dist-info/METADATA
focuspro_data533-0.0.1.dist-info/WHEEL
focuspro_data533-0.0.1.dist-info/entry_points.txt
focuspro_data533-0.0.1.dist-info/top_level.txt
focuspro_data533-0.0.1.dist-info/RECORD
