Metadata-Version: 2.4
Name: focuspro-data533
Version: 0.0.1
Summary: Educational productivity toolkit for tasks, habits, focus sessions, and analytics
Author-email: Inaara Rajwani <inaarari11@gmail.com>, Yusen Rong <yusenrong46@gmail.com>, Anita Zeng <zez321@student.ubc.ca>
License: MIT License
Project-URL: Homepage, https://github.com/inaararajwani11/data533_project
Project-URL: Issues, https://github.com/inaararajwani11/data533_project/issues
Classifier: Programming Language :: Python :: 3
Classifier: Programming Language :: Python :: 3 :: Only
Classifier: License :: OSI Approved :: MIT License
Classifier: Operating System :: OS Independent
Requires-Python: >=3.8
License-File: LICENSE
Dynamic: license-file
